LICENSE
README.md
pyproject.toml
setup.py
src/aicaliber/__init__.py
src/aicaliber.egg-info/PKG-INFO
src/aicaliber.egg-info/SOURCES.txt
src/aicaliber.egg-info/dependency_links.txt
src/aicaliber.egg-info/requires.txt
src/aicaliber.egg-info/top_level.txt
src/aicaliber/pytorch/__init__.py
src/aicaliber/pytorch/cv/__init__.py
src/aicaliber/pytorch/cv/callbacks.py
src/aicaliber/pytorch/cv/common.py
src/aicaliber/pytorch/cv/data_management.py
src/aicaliber/pytorch/cv/model.py
src/aicaliber/pytorch/cv/model_classes.py
src/aicaliber/pytorch/cv/model_zoo.py
src/aicaliber/pytorch/cv/param_selection.py
src/aicaliber/tensorflow/__init__.py
src/aicaliber/tensorflow/cv/__init__.py
src/aicaliber/tensorflow/cv/callbacks.py
src/aicaliber/tensorflow/cv/common.py
src/aicaliber/tensorflow/cv/data_management.py
src/aicaliber/tensorflow/cv/model.py
src/aicaliber/tensorflow/cv/model_zoo.py
src/aicaliber/tensorflow/cv/param_selection.py