Metadata-Version: 2.1
Name: aicaliber
Version: 0.0.8.post2
Summary: A high-level Python framework to automate the project lifecycle of Machine and Deep Learning Projects
Home-page: https://github.com/Hassi34/aicaliber
Author: Hasanain Mehmood
Author-email: hasanain@aicaliber.com
License: MIT
Project-URL: Bug Tracker, https://github.com/Hassi34/aicaliber/issues
Platform: UNKNOWN
Classifier: Development Status :: 5 - Production/Stable
Classifier: Intended Audience :: Developers
Classifier: Programming Language :: Python :: 3.7
Classifier: Programming Language :: Python :: 3.8
Classifier: Programming Language :: Python :: 3.9
Classifier: Programming Language :: Python :: 3.10
Classifier: License :: OSI Approved :: MIT License
Classifier: Topic :: Scientific/Engineering :: Artificial Intelligence
Classifier: Operating System :: OS Independent
Requires-Python: >=3.7
License-File: LICENSE
